{ "columns":13,
 "image":"tile.png",
 "imageheight":120,
 "imagewidth":520,
 "margin":0,
 "name":"Tiles",
 "spacing":0,
 "tilecount":39,
 "tiledversion":"1.2.2",
 "tileheight":40,
 "tiles":[
        {
         "id":12,
         "objectgroup":
            {
             "draworder":"index",
             "name":"",
             "objects":[
                    {
                     "height":0,
                     "id":1,
                     "name":"",
                     "polyline":[
                            {
                             "x":0,
                             "y":0
                            }, 
                            {
                             "x":-11,
                             "y":9.65625
                            }],
                     "rotation":0,
                     "type":"",
                     "visible":true,
                     "width":0,
                     "x":11.0625,
                     "y":0
                    }],
             "opacity":1,
             "type":"objectgroup",
             "visible":true,
             "x":0,
             "y":0
            }
        }, 
        {
         "id":19,
         "objectgroup":
            {
             "draworder":"index",
             "name":"",
             "objects":[
                    {
                     "height":0,
                     "id":1,
                     "name":"",
                     "polyline":[
                            {
                             "x":0,
                             "y":0
                            }, 
                            {
                             "x":-0.25,
                             "y":39.625
                            }],
                     "rotation":0,
                     "type":"",
                     "visible":true,
                     "width":0,
                     "x":6,
                     "y":0.25
                    }],
             "opacity":1,
             "type":"objectgroup",
             "visible":true,
             "x":0,
             "y":0
            }
        }],
 "tilewidth":40,
 "type":"tileset",
 "version":1.2
}